flash_services/__init__.py
flash_services/auth.py
flash_services/buddy.py
flash_services/circleci.py
flash_services/codeship.py
flash_services/core.py
flash_services/coveralls.py
flash_services/github.py
flash_services/jenkins.py
flash_services/tracker.py
flash_services/travis.py
flash_services/utils.py
flash_services/static/scripts/services.js
flash_services/templates/partials/coveralls-section.html
flash_services/templates/partials/gh-issues-section.html
flash_services/templates/partials/tracker-section.html
flash_services-0.12.3.dist-info/LICENSE
flash_services-0.12.3.dist-info/METADATA
flash_services-0.12.3.dist-info/WHEEL
flash_services-0.12.3.dist-info/top_level.txt
flash_services-0.12.3.dist-info/RECORD
