Metadata-Version: 2.1
Name: flash-services
Version: 0.12.3
Summary: The services that can be shown on a Flash dashboard.
Home-page: http://github.com/textbook/flash/
Author: Jonathan Sharpe
Author-email: mail@jonrshar.pe
License: License :: OSI Approved :: ISC License (ISCL)
Platform: any
Classifier: Development Status :: 3 - Alpha
Classifier: Intended Audience :: Developers
Classifier: Natural Language :: English
Classifier: Operating System :: OS Independent
Classifier: Programming Language :: Python :: 3.9
Classifier: Programming Language :: Python :: 3 :: Only
License-File: LICENSE
Requires-Dist: Flask
Requires-Dist: humanize
Requires-Dist: python-dateutil
Requires-Dist: requests
